reconciler/__init__.py
reconciler/reconciler.py
tests/__init__.py
tests/test_reconciler.py
aminimalreconciler-0.1.4.dist-info/METADATA
aminimalreconciler-0.1.4.dist-info/WHEEL
aminimalreconciler-0.1.4.dist-info/entry_points.txt
aminimalreconciler-0.1.4.dist-info/top_level.txt
aminimalreconciler-0.1.4.dist-info/RECORD
