Metadata-Version: 2.1
Name: aminimalreconciler
Version: 0.1.4
Summary: reconciler
Home-page: https://github.com/muathendirangu/reconcile
Author: muathendirangu
Author-email: muathe.ndirangu@gmail.com
License: MIT
